mapvu/__init__.py
mapvu/common.py
mapvu/foliummap.py
mapvu/mapvu.py
mapvu-0.0.4.dist-info/licenses/LICENSE
mapvu-0.0.4.dist-info/METADATA
mapvu-0.0.4.dist-info/WHEEL
mapvu-0.0.4.dist-info/dependency_links.txt
mapvu-0.0.4.dist-info/top_level.txt
mapvu-0.0.4.dist-info/RECORD
